kojichannelvalidator/__init__.py
kojichannelvalidator/__main__.py
kojichannelvalidator/koji_channel_validator.py
KojiChannelValidator-0.1.1.dist-info/LICENSE
KojiChannelValidator-0.1.1.dist-info/METADATA
KojiChannelValidator-0.1.1.dist-info/WHEEL
KojiChannelValidator-0.1.1.dist-info/entry_points.txt
KojiChannelValidator-0.1.1.dist-info/top_level.txt
KojiChannelValidator-0.1.1.dist-info/RECORD
